<CompuCell3D>
    <Potts>
        <Dimensions x="200" y="200" z="1"/> <!-- Z >1 become 3D -->
        <Anneal>10</Anneal>
        <Steps>1000000</Steps>
        <Temperature>5</Temperature>
        <Flip2DimRatio>1</Flip2DimRatio>
        <Boundary_x>Periodic</Boundary_x>
        <Boundary_y>Periodic</Boundary_y>
        <NeighborOrder>2</NeighborOrder>
    </Potts>

    <Plugin Name="Volume">
        <TargetVolume>25</TargetVolume>
        <LambdaVolume>1</LambdaVolume>
    </Plugin>


    <Plugin Name="CenterOfMass"/>

    <Plugin Name="CellType">
        <CellType TypeName="Medium" TypeId="0"/>
        <CellType TypeName="CadExpLevel1" TypeId="1"/>
        <CellType TypeName="CadExpLevel2" TypeId="2"/>
    </Plugin>


    <Plugin Name="ContactLocalProduct">

        <ContactSpecificity Type1="Medium" Type2="Medium">0</ContactSpecificity>
        <ContactSpecificity Type1="Medium" Type2="CadExpLevel1">-16</ContactSpecificity>
        <ContactSpecificity Type1="Medium" Type2="CadExpLevel2">-16</ContactSpecificity>
        <ContactSpecificity Type1="CadExpLevel1" Type2="CadExpLevel1">-2</ContactSpecificity>
        <ContactSpecificity Type1="CadExpLevel1" Type2="CadExpLevel2">-2.75</ContactSpecificity>
        <ContactSpecificity Type1="CadExpLevel2" Type2="CadExpLevel2">-1</ContactSpecificity>

        <EnergyOffset>0.0</EnergyOffset>
        <NeighborOrder>2</NeighborOrder>
    </Plugin>


    <Steppable Type="BlobInitializer">
        <Region>
            <Center x="100" y="100" z="0"/>
            <Radius>50</Radius>
            <Gap>0</Gap>
            <Width>5</Width>
            <Types>CadExpLevel1,CadExpLevel2</Types>
        </Region>
    </Steppable>


</CompuCell3D>
